taosaypypi/__init__.py
taosaypypi/cli.py
taosaypypi/taosaypypi.py
taosaypypi-0.1.0.dist-info/AUTHORS.rst
taosaypypi-0.1.0.dist-info/LICENSE
taosaypypi-0.1.0.dist-info/METADATA
taosaypypi-0.1.0.dist-info/WHEEL
taosaypypi-0.1.0.dist-info/entry_points.txt
taosaypypi-0.1.0.dist-info/top_level.txt
taosaypypi-0.1.0.dist-info/RECORD
