Metadata-Version: 2.1
Name: taosaypypi
Version: 0.1.0
Summary: just test pypi
Home-page: https://github.com/sit-in/taosaypypi
Author: sitin me
Author-email: 257735@qq.com
License: MIT license
Keywords: taosaypypi
Platform: UNKNOWN
Classifier: Development Status :: 2 - Pre-Alpha
Classifier: Intended Audience :: Developers
Classifier: License :: OSI Approved :: MIT License
Classifier: Natural Language :: English
Classifier: Programming Language :: Python :: 3
Classifier: Programming Language :: Python :: 3.6
Classifier: Programming Language :: Python :: 3.7
Classifier: Programming Language :: Python :: 3.8
Requires-Python: >=3.6
Requires-Dist: Click (>=7.0)
